pycountssu1/__init__.py
pycountssu1/plotting.py
pycountssu1/pycountssu1.py
pycountssu1-0.1.0.dist-info/LICENSE
pycountssu1-0.1.0.dist-info/METADATA
pycountssu1-0.1.0.dist-info/WHEEL
pycountssu1-0.1.0.dist-info/RECORD
