Metadata-Version: 2.1
Name: pycountssu1
Version: 0.1.0
Summary: Toy Package for DSCI 524 that counts words in given text.
License: MIT
Author: Salva Umar
Requires-Python: >=3.9
Classifier: License :: OSI Approved :: MIT License
Classifier: Programming Language :: Python :: 3
Classifier: Programming Language :: Python :: 3.9
Classifier: Programming Language :: Python :: 3.10
Classifier: Programming Language :: Python :: 3.11
Classifier: Programming Language :: Python :: 3.12
Requires-Dist: matplotlib (>=3.8.2)
